noct/__init__.py
noct/cli.py
noct/schema/__init__.py
noct/schema/attachment/__init__.py
noct/schema/attachment/action.py
noct/schema/attachment/attachment.py
noct/schema/block/__init__.py
noct/schema/block/divider.py
noct/schema/block/field.py
noct/schema/block/plain_text.py
noct/schema/block/section.py
noct/schema/slack.py
noct-0.1.5.dist-info/entry_points.txt
noct-0.1.5.dist-info/LICENSE
noct-0.1.5.dist-info/WHEEL
noct-0.1.5.dist-info/METADATA
noct-0.1.5.dist-info/RECORD
