Metadata-Version: 2.1
Name: noct
Version: 0.1.5
Summary: Command Line Notification Tool
License: Apache-2.0
Author: Naoya Sawada
Author-email: naoya@tuntunkun.com
Requires-Python: >=3.6,<4.0
Classifier: License :: OSI Approved :: Apache Software License
Classifier: Programming Language :: Python :: 3
Classifier: Programming Language :: Python :: 3.6
Classifier: Programming Language :: Python :: 3.7
Classifier: Programming Language :: Python :: 3.8
Requires-Dist: click (>=7.1.2,<8.0.0)
Requires-Dist: requests (>=2.23.0,<3.0.0)
